{"User.0d6701cc-d5b8-491d-8508-f8c7e90e46cf": {"first_name": "Mohamed", "last_name": "Khaled", "email": "mokhaled2004@gmail.com", "password": "7dd10b96fbf185230ef6e9f8201e2ba1", "address": "7832 Mohamed Ibrahim street, Region C Mokattam", "phone": "01097757050", "rating": 5, "created_at": "2024-07-08T19:39:25.816671", "updated_at": "2024-07-08T19:39:25.816671", "id": "0d6701cc-d5b8-491d-8508-f8c7e90e46cf", "photo": "https://encrypted-tbn0.gstatic.com/images?q=tbn:ANd9GcQ_gB8nb_Od3Yo1bZRHIZLcDe2N-pQu5XA96g&s", "__class__": "User"}, "User.55a716e4-0ce2-491a-95d9-e32a3d7a4b27": {"first_name": "Mohamed", "last_name": "yasser", "email": "yasser@gmail.com", "password": "f933d9cc10392bc05b01bc1e2b2241e7", "address": "7832 Mohamed Ibrahim street, Region C Mokattam", "phone": "01097757050", "rating": 4, "created_at": "2024-07-08T19:40:04.367265", "updated_at": "2024-07-08T19:40:04.367265", "id": "55a716e4-0ce2-491a-95d9-e32a3d7a4b27", "__class__": "User"}}